overload/__init__.py
overload/client.py
overload/exceptions.py
overload_ai-1.1.0.dist-info/licenses/LICENSE
overload_ai-1.1.0.dist-info/METADATA
overload_ai-1.1.0.dist-info/WHEEL
overload_ai-1.1.0.dist-info/top_level.txt
overload_ai-1.1.0.dist-info/RECORD
