Metadata-Version: 2.4
Name: overload-ai
Version: 1.1.0
Summary: AI-powered Python bug identification client
Author-email: Chisom life eke <your.email@example.com>
Maintainer-email: Chisom life eke <your.email@example.com>
License-Expression: MIT
Project-URL: Homepage, https://github.com/QRTQuick/overload
Project-URL: Documentation, https://github.com/QRTQuick/overload#readme
Project-URL: Repository, https://github.com/QRTQuick/overload.git
Project-URL: Issues, https://github.com/QRTQuick/overload/issues
Project-URL: Changelog, https://github.com/QRTQuick/overload/blob/main/CHANGELOG.md
Keywords: python,ai,bug-detection,static-analysis,linting
Classifier: Development Status :: 4 - Beta
Classifier: Intended Audience :: Developers
Classifier: Operating System :: OS Independent
Classifier: Programming Language :: Python :: 3
Classifier: Programming Language :: Python :: 3.8
Classifier: Programming Language :: Python :: 3.9
Classifier: Programming Language :: Python :: 3.10
Classifier: Programming Language :: Python :: 3.11
Classifier: Programming Language :: Python :: 3.12
Classifier: Topic :: Software Development :: Quality Assurance
Classifier: Topic :: Software Development :: Libraries :: Python Modules
Requires-Python: >=3.8
License-File: LICENSE
Requires-Dist: requests>=2.25.0
Dynamic: license-file
